hack_quest/__init__.py
hack_quest/main.py
hack_quest_cli-1.0.3.dist-info/licenses/LICENSE
hack_quest_cli-1.0.3.dist-info/METADATA
hack_quest_cli-1.0.3.dist-info/WHEEL
hack_quest_cli-1.0.3.dist-info/entry_points.txt
hack_quest_cli-1.0.3.dist-info/top_level.txt
hack_quest_cli-1.0.3.dist-info/RECORD
