Metadata-Version: 2.4
Name: hack-quest-cli
Version: 1.0.3
Summary: A CLI adventure game where you play as a hacker trying to break into a bank vault.
Author-email: Samy0_o <samytonygo@gmail.com>
License: MIT
Requires-Python: >=3.7
License-File: LICENSE
Requires-Dist: rich
Dynamic: license-file
